robocore/__init__.py
robocore/config.py
robocore/kvstore.py
robocore/messaging.py
robocore/registry.py
robocore/server.py
robocore/utils.py
robocore/visualization.py
robocore-0.0.1.dist-info/LICENSE
robocore-0.0.1.dist-info/METADATA
robocore-0.0.1.dist-info/WHEEL
robocore-0.0.1.dist-info/top_level.txt
robocore-0.0.1.dist-info/RECORD
