Metadata-Version: 2.1
Name: robocore
Version: 0.0.1
Summary: A Python middleware for robotic communication.
Home-page: https://github.com/pthangeda/robocore
Author: Pranay Thangeda
Author-email: contact@prny.me
License: MIT
Keywords: robotics communication middleware
Classifier: Programming Language :: Python :: 3
Classifier: Operating System :: OS Independent
Requires-Python: >=3.6
License-File: LICENSE
Requires-Dist: pyzmq >=22.0.0
Requires-Dist: PyYAML >=5.4
Requires-Dist: rerun-sdk >=0.19.0
